maven_settings_decoder/__init__.py
maven_settings_decoder/__main__.py
maven_settings_decoder/decode.py
maven_settings_decoder-0.1.1.dist-info/LICENSE
maven_settings_decoder-0.1.1.dist-info/METADATA
maven_settings_decoder-0.1.1.dist-info/WHEEL
maven_settings_decoder-0.1.1.dist-info/entry_points.txt
maven_settings_decoder-0.1.1.dist-info/RECORD
