Metadata-Version: 2.1
Name: maven_settings_decoder
Version: 0.1.1
Summary: Decode mavens settings.xml file
License: MIT
Author: Steven Van Ingelgem
Author-email: steven@vaningelgem.be
Requires-Python: >=3.9,<4.0
Classifier: License :: OSI Approved :: MIT License
Classifier: Programming Language :: Python :: 3
Classifier: Programming Language :: Python :: 3.9
Classifier: Programming Language :: Python :: 3.10
Classifier: Programming Language :: Python :: 3.11
Classifier: Programming Language :: Python :: 3.12
Requires-Dist: cryptography
Requires-Dist: loguru
